{
  "crest_base_url": "https://www.fifaindex.com/static/FIFA18WC/images/crestwc/256/light/",
  "teams": [
    {
      "name": "Greece",
      "attack": "75",
      "midfield": "74",
      "defense": "77",
      "overall": "75",
      "rating": "35",
      "crest_id": "1338.png"
    },
    {
      "name": "IR Iran",
      "attack": "79",
      "midfield": "71",
      "defense": "70",
      "overall": "74",
      "rating": "35",
      "crest_id": "111115.png"
    },
    {
      "name": "Scotland",
      "attack": "75",
      "midfield": "74",
      "defense": "74",
      "overall": "74",
      "rating": "35",
      "crest_id": "1359.png"
    },
    {
      "name": "Korea Republic",
      "attack": "74",
      "midfield": "74",
      "defense": "69",
      "overall": "73",
      "rating": "35",
      "crest_id": "974.png"
    },
    {
      "name": "Northern Ireland",
      "attack": "74",
      "midfield": "73",
      "defense": "72",
      "overall": "73",
      "rating": "35",
      "crest_id": "110081.png"
    },
    {
      "name": "Norway",
      "attack": "74",
      "midfield": "73",
      "defense": "72",
      "overall": "73",
      "rating": "35",
      "crest_id": "1352.png"
    },
    {
      "name": "Czech Republic",
      "attack": "73",
      "midfield": "74",
      "defense": "72",
      "overall": "73",
      "rating": "35",
      "crest_id": "1330.png"
    },
    {
      "name": "Tunisia",
      "attack": "73",
      "midfield": "72",
      "defense": "72",
      "overall": "73",
      "rating": "35",
      "crest_id": "1391.png"
    },
    {
      "name": "Costa Rica",
      "attack": "69",
      "midfield": "73",
      "defense": "73",
      "overall": "73",
      "rating": "35",
      "crest_id": "1383.png"
    },
    {
      "name": "Romania",
      "attack": "74",
      "midfield": "71",
      "defense": "69",
      "overall": "72",
      "rating": "35",
      "crest_id": "1356.png"
    },
    {
      "name": "Saudi Arabia",
      "attack": "71",
      "midfield": "72",
      "defense": "71",
      "overall": "72",
      "rating": "35",
      "crest_id": "111114.png"
    },
    {
      "name": "Australia",
      "attack": "69",
      "midfield": "72",
      "defense": "70",
      "overall": "72",
      "rating": "35",
      "crest_id": "1415.png"
    }
  ]
}
